flask_httpclient.py
Flask_HTTPClient-1.1.dist-info/LICENSE
Flask_HTTPClient-1.1.dist-info/METADATA
Flask_HTTPClient-1.1.dist-info/WHEEL
Flask_HTTPClient-1.1.dist-info/top_level.txt
Flask_HTTPClient-1.1.dist-info/RECORD
