Metadata-Version: 2.1
Name: Flask-HTTPClient
Version: 1.1
Summary: HTTP Client extension for Flask
Home-page: https://github.com/haojunyu/flask-httpclient
Author: haojunyu
Author-email: haojunyu2012@gmail.com
License: MIT
Platform: any
Classifier: Environment :: Web Environment
Classifier: Intended Audience :: Developers
Classifier: License :: OSI Approved :: MIT License
Classifier: Operating System :: OS Independent
Classifier: Programming Language :: Python :: 3
Classifier: Topic :: Internet :: WWW/HTTP :: Dynamic Content
Classifier: Topic :: Software Development :: Libraries :: Python Modules
Requires-Dist: Flask
Requires-Dist: requests
